fastapi_helpers/__init__.py
fastapi_helpers/py.typed
fastapi_helpers/cache/__init__.py
fastapi_helpers/core/__init__.py
fastapi_helpers/core/logging/DefaultLogger.py
fastapi_helpers/core/logging/__init__.py
fastapi_helpers/core/settings/DefaultSettings.py
fastapi_helpers/core/settings/__init__.py
fastapi_helpers/crud/BaseCrud.py
fastapi_helpers/crud/__init__.py
fastapi_helpers/db/DbConfig.py
fastapi_helpers/db/__init__.py
fastapi_helpers/db/seeders/__init__.py
fastapi_helpers/db/seeders/reader.py
fastapi_helpers/models/__init__.py
fastapi_helpers/routes/Paginate.py
fastapi_helpers/routes/__init__.py
fastapi_helpers/routes/middlewares/HeadersMiddleware.py
fastapi_helpers/routes/middlewares/IpAccessMiddleware.py
fastapi_helpers/routes/middlewares/__init__.py
fastapi_helpers/routes/middlewares/get_real_ip.py
fastapi_helpers/routes/models/PaginateOptions.py
fastapi_helpers/routes/models/PaginateResult.py
fastapi_helpers/routes/models/__init__.py
fastapi_helpers/routes/routers/DefaultModelRouter.py
fastapi_helpers/routes/routers/RouterGenerator.py
fastapi_helpers/routes/routers/__init__.py
fastapi_helpers/security/__init__.py
fastapi_helpers/workers/__init__.py
fastapi_helpers-0.3.0.data/data/LICENSE.md
fastapi_helpers-0.3.0.dist-info/LICENSE.md
fastapi_helpers-0.3.0.dist-info/METADATA
fastapi_helpers-0.3.0.dist-info/WHEEL
fastapi_helpers-0.3.0.dist-info/top_level.txt
fastapi_helpers-0.3.0.dist-info/zip-safe
fastapi_helpers-0.3.0.dist-info/RECORD
