Metadata-Version: 2.1
Name: fastapi-helpers
Version: 0.3.0
Summary: An utils package for fastapi
Home-page: https://github.com/finalsa/fastapi-utils
Author: Luis Jimenez
Author-email: luis@finalsa.com
License: MIT
Keywords: fastapi,sqlalchemy,ormar,pydantic
Classifier: Intended Audience :: Developers
Classifier: License :: OSI Approved :: BSD License
Classifier: Operating System :: OS Independent
Classifier: Topic :: Internet :: WWW/HTTP
Classifier: Programming Language :: Python :: 3
Classifier: Programming Language :: Python :: 3.7
Classifier: Programming Language :: Python :: 3.8
Classifier: Programming Language :: Python :: 3.9
Classifier: Programming Language :: Python :: 3.10
Requires-Python: >=3.8
License-File: LICENSE.md
Requires-Dist: argon2-cffi >=23.1.0
Requires-Dist: aiosqlite >=0.19.0
Requires-Dist: ormar >=0.12.2
Requires-Dist: pydantic >=1.10.8
Requires-Dist: fastapi >=0.105.0
Requires-Dist: fastapi-better-logger >=0.0.5
Requires-Dist: typing-extensions >=4.9.0
Requires-Dist: watchtower >=3.0.0
Requires-Dist: boto3 >=1.20.3
Provides-Extra: mysql
Requires-Dist: aiomysql ; extra == 'mysql'
Requires-Dist: pymysql ; extra == 'mysql'
Provides-Extra: orjson
Requires-Dist: orjson ; extra == 'orjson'
Provides-Extra: postgresql
Requires-Dist: asyncpg ; extra == 'postgresql'
Requires-Dist: psycopg2-binary ; extra == 'postgresql'
Provides-Extra: sqlite
Requires-Dist: aiosqlite ; extra == 'sqlite'
